_gojsonnet.cpython-313-darwin.so
gojsonnet-0.21.0.dist-info/RECORD
gojsonnet-0.21.0.dist-info/WHEEL
gojsonnet-0.21.0.dist-info/top_level.txt
gojsonnet-0.21.0.dist-info/METADATA
gojsonnet-0.21.0.dist-info/licenses/LICENSE
