Metadata-Version: 2.4
Name: gojsonnet
Version: 0.21.0
Summary: Python bindings for Jsonnet - The data templating language 
Home-page: https://jsonnet.org
Author: David Cunningham
Author-email: dcunnin@google.com
License-File: LICENSE
Dynamic: author
Dynamic: author-email
Dynamic: home-page
Dynamic: license-file
Dynamic: summary
